ostris_ai_toolkit/__init__.py
ostris_ai_toolkit/flux_train_ui.py
ostris_ai_toolkit/info.py
ostris_ai_toolkit/run.py
ostris_ai_toolkit/run_modal.py
ostris_ai_toolkit/config/examples/extract.example.yml
ostris_ai_toolkit/config/examples/generate.example.yaml
ostris_ai_toolkit/config/examples/mod_lora_scale.yaml
ostris_ai_toolkit/config/examples/train_lora_flux_24gb.yaml
ostris_ai_toolkit/config/examples/train_lora_flux_schnell_24gb.yaml
ostris_ai_toolkit/config/examples/train_lora_sd35_large_24gb.yaml
ostris_ai_toolkit/config/examples/train_slider.example.yml
ostris_ai_toolkit/config/examples/modal/modal_train_lora_flux_24gb.yaml
ostris_ai_toolkit/config/examples/modal/modal_train_lora_flux_schnell_24gb.yaml
ostris_ai_toolkit/extensions/example/ExampleMergeModels.py
ostris_ai_toolkit/extensions/example/__init__.py
ostris_ai_toolkit/extensions/example/config/config.example.yaml
ostris_ai_toolkit/extensions_built_in/__init__.py
ostris_ai_toolkit/extensions_built_in/advanced_generator/Img2ImgGenerator.py
ostris_ai_toolkit/extensions_built_in/advanced_generator/PureLoraGenerator.py
ostris_ai_toolkit/extensions_built_in/advanced_generator/ReferenceGenerator.py
ostris_ai_toolkit/extensions_built_in/advanced_generator/__init__.py
ostris_ai_toolkit/extensions_built_in/advanced_generator/config/train.example.yaml
ostris_ai_toolkit/extensions_built_in/concept_replacer/ConceptReplacer.py
ostris_ai_toolkit/extensions_built_in/concept_replacer/__init__.py
ostris_ai_toolkit/extensions_built_in/concept_replacer/config/train.example.yaml
ostris_ai_toolkit/extensions_built_in/dataset_tools/DatasetTools.py
ostris_ai_toolkit/extensions_built_in/dataset_tools/SuperTagger.py
ostris_ai_toolkit/extensions_built_in/dataset_tools/SyncFromCollection.py
ostris_ai_toolkit/extensions_built_in/dataset_tools/__init__.py
ostris_ai_toolkit/extensions_built_in/dataset_tools/tools/caption.py
ostris_ai_toolkit/extensions_built_in/dataset_tools/tools/dataset_tools_config_modules.py
ostris_ai_toolkit-0.2.7.dist-info/LICENSE
ostris_ai_toolkit-0.2.7.dist-info/METADATA
ostris_ai_toolkit-0.2.7.dist-info/WHEEL
ostris_ai_toolkit-0.2.7.dist-info/top_level.txt
ostris_ai_toolkit-0.2.7.dist-info/RECORD
