Metadata-Version: 2.1
Name: ostris-ai-toolkit
Version: 0.2.7
Summary: A toolkit for AI-related tasks
Author-email: Cozy Creator <teggyg123@gmail.com>
License: MIT License
Project-URL: Homepage, https://github.com/ostris/ai-toolkit
Project-URL: Bug Tracker, https://github.com/ostris/ai-toolkit/issues
Classifier: Programming Language :: Python :: 3
Classifier: License :: OSI Approved :: MIT License
Classifier: Operating System :: OS Independent
Requires-Python: >=3.10
License-File: LICENSE
Requires-Dist: torch
Requires-Dist: torchvision
Requires-Dist: safetensors
Requires-Dist: diffusers
Requires-Dist: transformers
Requires-Dist: lycoris-lora==1.8.3
Requires-Dist: flatten-json
Requires-Dist: pyyaml
Requires-Dist: oyaml
Requires-Dist: tensorboard
Requires-Dist: kornia
Requires-Dist: invisible-watermark
Requires-Dist: einops
Requires-Dist: accelerate
Requires-Dist: toml
Requires-Dist: albumentations
Requires-Dist: pydantic
Requires-Dist: omegaconf
Requires-Dist: k-diffusion
Requires-Dist: open-clip-torch
Requires-Dist: timm
Requires-Dist: prodigyopt
Requires-Dist: controlnet-aux==0.0.7
Requires-Dist: python-dotenv
Requires-Dist: bitsandbytes
Requires-Dist: hf-transfer
Requires-Dist: lpips
Requires-Dist: pytorch-fid
Requires-Dist: optimum-quanto
Requires-Dist: sentencepiece
Requires-Dist: huggingface-hub
Requires-Dist: peft
Requires-Dist: gradio
Requires-Dist: python-slugify
